pyfastcom/__init__.py
pyfastcom/_api.py
pyfastcom/version.py
pyfastcom-1.1.0.dist-info/LICENSE
pyfastcom-1.1.0.dist-info/METADATA
pyfastcom-1.1.0.dist-info/WHEEL
pyfastcom-1.1.0.dist-info/top_level.txt
pyfastcom-1.1.0.dist-info/RECORD
