Metadata-Version: 2.1
Name: pyfastcom
Version: 1.1.0
Summary: Python API that gets the results from fast.com test using Selenium
Home-page: https://github.com/ppizarror/pyfastcom
Author: ppizarror
Author-email: pablo@ppizarror.com
License: MIT
Project-URL: Bug Tracker, https://github.com/ppizarror/pyfastcom/issues
Project-URL: Documentation, https://github.com/ppizarror/pyfastcom
Project-URL: Source Code, https://github.com/ppizarror/pyfastcom
Keywords: fast.com selenium internet velocity speed scrapper
Platform: any
Classifier: License :: OSI Approved :: MIT License
Classifier: Natural Language :: English
Classifier: Operating System :: OS Independent
Classifier: Programming Language :: Python :: 3.5
Classifier: Programming Language :: Python :: 3.6
Classifier: Programming Language :: Python :: 3.7
Classifier: Programming Language :: Python :: 3.8
Classifier: Programming Language :: Python :: 3.9
Classifier: Programming Language :: Python
Classifier: Topic :: Games/Entertainment
Classifier: Topic :: Multimedia
Requires-Python: >=3, <4
Requires-Dist: bs4
Requires-Dist: selenium
